vidtoolz_hum_hai_rahi/__init__.py
vidtoolz_hum_hai_rahi-0.0.3.dist-info/licenses/LICENSE
vidtoolz_hum_hai_rahi-0.0.3.dist-info/METADATA
vidtoolz_hum_hai_rahi-0.0.3.dist-info/WHEEL
vidtoolz_hum_hai_rahi-0.0.3.dist-info/entry_points.txt
vidtoolz_hum_hai_rahi-0.0.3.dist-info/top_level.txt
vidtoolz_hum_hai_rahi-0.0.3.dist-info/RECORD
