Metadata-Version: 2.4
Name: vidtoolz-hum-hai-rahi
Version: 0.0.3
Summary: Tools for hum hai rahi channel
Author: Sukhbinder Singh
License: Apache-2.0
Project-URL: Homepage, https://github.com/sukhbinder/vidtoolz-hum-hai-rahi
Project-URL: Changelog, https://github.com/sukhbinder/vidtoolz-hum-hai-rahi/releases
Project-URL: Issues, https://github.com/sukhbinder/vidtoolz-hum-hai-rahi/issues
Project-URL: CI, https://github.com/sukhbinder/vidtoolz-hum-hai-rahi/actions
Classifier: License :: OSI Approved :: Apache Software License
License-File: LICENSE
Requires-Dist: vidtoolz
Requires-Dist: vidtoolz-apply-greenscreen
Requires-Dist: vidtoolz-add-sound
Provides-Extra: test
Requires-Dist: pytest; extra == "test"
Dynamic: license-file
